vnauto/__init__.py
vnauto/convert_datetime.py
vnauto/convert_number.py
vnauto/convert_total.py
vnauto/convert_win1252_to_utf8.py
vnauto/data_loader.py
vnauto/remove_character.py
vnauto/remove_duplicate_emoji.py
vnauto/remove_stopword.py
vnauto/remove_token.py
vnauto/standardize_total.py
vnauto/vnauto_score.py
vnauto/data/Acronyms.txt
vnauto/data/Acronyms_shorten.txt
vnauto/data/BaseUnit.txt
vnauto/data/CurrencyUnit.txt
vnauto/data/Number.txt
vnauto/data/PrefixUnit.txt
vnauto/data/Symbol.txt
vnauto/data/Teencode.txt
vnauto/data/emojicon.txt
vnauto/data/vietnamese-stopwords.txt
vnauto-1.0.0.dist-info/METADATA
vnauto-1.0.0.dist-info/WHEEL
vnauto-1.0.0.dist-info/top_level.txt
vnauto-1.0.0.dist-info/RECORD
