Metadata-Version: 2.1
Name: vnauto
Version: 1.0.0
Summary: A Python library for Vietnamese text normalization and processing
Home-page: https://github.com/Truong-itt/vnauto
Author: TruongItt
Author-email: hoduytruong280220@gmail.com
License: MIT
Platform: UNKNOWN
Classifier: Programming Language :: Python :: 3
Classifier: License :: OSI Approved :: MIT License
Classifier: Operating System :: OS Independent
Requires-Python: >=3.6
Requires-Dist: pandas>=1.0.0
Requires-Dist: setuptools
Requires-Dist: underthesea>=1.3.5
